.semver
LICENSE.rst
MANIFEST.in
README.rst
requirements.txt
setup.py
detective/Driver.py
detective/Scanner.py
detective/__init__.py
detective.egg-info/PKG-INFO
detective.egg-info/SOURCES.txt
detective.egg-info/dependency_links.txt
detective.egg-info/entry_points.txt
detective.egg-info/requires.txt
detective.egg-info/top_level.txt
detective/actions/AppendToUrlAction.py
detective/actions/BaseAction.py
detective/actions/ReplaceExtensionAction.py
detective/actions/TraverseInUrlAction.py
detective/actions/__init__.py
detective/helpers/PackageHelper.py
detective/helpers/__init__.py
detective_scripts/__init__.py
detective_scripts/detective_cli.py