Metadata-Version: 1.1
Name: detective
Version: 1.0.2
Summary: A private detective that gathers information you're not supposed to know about.
Home-page: https://github.com/tijme/detective
Author: Tijme Gommers
Author-email: detective@finnwea.com
License: MIT
Keywords: vulnerability,bug-bounty,security,information-disclosure,sensitive-data-exposure,scanner
Platform: any
Classifier: Development Status :: 5 - Production/Stable
Classifier: Environment :: Console
Classifier: Intended Audience :: Developers
Classifier: Intended Audience :: Education
Classifier: Intended Audience :: Information Technology
Classifier: Intended Audience :: System Administrators
Classifier: License :: OSI Approved :: MIT License
Classifier: Natural Language :: English
Classifier: Operating System :: MacOS
Classifier: Operating System :: Microsoft :: Windows
Classifier: Operating System :: POSIX :: Linux
Classifier: Programming Language :: Python :: 3.6
Classifier: Programming Language :: Python :: 3.5
Classifier: Programming Language :: Python :: 3.4
Classifier: Programming Language :: Python :: 3.3
Classifier: Programming Language :: Python :: 2.7
Classifier: Topic :: Security
